{"id":"index.js","dependencies":[{"name":"/Users/kamgang/Desktop/parcel-js/package.json","includedInParent":true,"mtime":1535892710000},{"name":"./styles/styles.scss","loc":{"line":1,"column":7},"parent":"/Users/kamgang/Desktop/parcel-js/index.js","resolved":"/Users/kamgang/Desktop/parcel-js/styles/styles.scss"},{"name":"flexboxgrid","loc":{"line":2,"column":7},"parent":"/Users/kamgang/Desktop/parcel-js/index.js","resolved":"/Users/kamgang/Desktop/parcel-js/node_modules/flexboxgrid/dist/flexboxgrid.css"},{"name":"./js/text.js","loc":{"line":3,"column":7},"parent":"/Users/kamgang/Desktop/parcel-js/index.js","resolved":"/Users/kamgang/Desktop/parcel-js/js/text.js"}],"generated":{"js":"'use strict';\n\nrequire('./styles/styles.scss');\n\nrequire('flexboxgrid');\n\nrequire('./js/text.js');\n\n$(\".features_home\").animate({\n  top: \"0%\",\n  height: \"100%\"\n}, 1000, function () {\n  $(\".features_home\").animate({\n    left: \"0px\",\n    width: \"50%\"\n\n  }, 900, function () {\n    $(\".features_text\").fadeIn(2000, function () {\n      $(\".features_text\").hide(900);\n      $(\".features_home\").animate({\n\n        width: \"35%\"\n      }, 500, function () {\n        $(\".features_img\").animate({\n          height: \"70%\"\n        }, 500, function () {\n          $(\".features_img\").animate({\n            width: \"30%\"\n          }, 500);\n        });\n      });\n    });\n  });\n});","map":{"mappings":[{"generated":{"line":3,"column":0},"source":"index.js","original":{"line":1,"column":0}},{"generated":{"line":5,"column":0},"source":"index.js","original":{"line":2,"column":0}},{"generated":{"line":7,"column":0},"source":"index.js","original":{"line":3,"column":0}},{"name":"$","generated":{"line":9,"column":0},"source":"index.js","original":{"line":5,"column":0}},{"generated":{"line":9,"column":2},"source":"index.js","original":{"line":5,"column":2}},{"generated":{"line":9,"column":18},"source":"index.js","original":{"line":5,"column":0}},{"name":"animate","generated":{"line":9,"column":20},"source":"index.js","original":{"line":5,"column":20}},{"generated":{"line":9,"column":27},"source":"index.js","original":{"line":5,"column":0}},{"generated":{"line":9,"column":28},"source":"index.js","original":{"line":5,"column":28}},{"name":"top","generated":{"line":10,"column":0},"source":"index.js","original":{"line":6,"column":2}},{"generated":{"line":10,"column":7},"source":"index.js","original":{"line":6,"column":7}},{"generated":{"line":10,"column":11},"source":"index.js","original":{"line":5,"column":28}},{"name":"height","generated":{"line":11,"column":0},"source":"index.js","original":{"line":7,"column":2}},{"generated":{"line":11,"column":10},"source":"index.js","original":{"line":7,"column":10}},{"generated":{"line":12,"column":0},"source":"index.js","original":{"line":5,"column":28}},{"generated":{"line":12,"column":1},"source":"index.js","original":{"line":5,"column":0}},{"generated":{"line":12,"column":3},"source":"index.js","original":{"line":8,"column":3}},{"generated":{"line":12,"column":7},"source":"index.js","original":{"line":5,"column":0}},{"generated":{"line":12,"column":9},"source":"index.js","original":{"line":8,"column":9}},{"generated":{"line":12,"column":21},"source":"index.js","original":{"line":8,"column":20}},{"name":"$","generated":{"line":13,"column":0},"source":"index.js","original":{"line":9,"column":2}},{"generated":{"line":13,"column":4},"source":"index.js","original":{"line":9,"column":4}},{"generated":{"line":13,"column":20},"source":"index.js","original":{"line":9,"column":2}},{"name":"animate","generated":{"line":13,"column":22},"source":"index.js","original":{"line":9,"column":22}},{"generated":{"line":13,"column":29},"source":"index.js","original":{"line":9,"column":2}},{"generated":{"line":13,"column":30},"source":"index.js","original":{"line":9,"column":30}},{"name":"left","generated":{"line":14,"column":0},"source":"index.js","original":{"line":10,"column":4}},{"generated":{"line":14,"column":10},"source":"index.js","original":{"line":10,"column":10}},{"generated":{"line":14,"column":15},"source":"index.js","original":{"line":9,"column":30}},{"name":"width","generated":{"line":15,"column":0},"source":"index.js","original":{"line":11,"column":4}},{"generated":{"line":15,"column":11},"source":"index.js","original":{"line":11,"column":11}},{"generated":{"line":17,"column":0},"source":"index.js","original":{"line":9,"column":30}},{"generated":{"line":17,"column":3},"source":"index.js","original":{"line":9,"column":2}},{"generated":{"line":17,"column":5},"source":"index.js","original":{"line":13,"column":5}},{"generated":{"line":17,"column":8},"source":"index.js","original":{"line":9,"column":2}},{"generated":{"line":17,"column":10},"source":"index.js","original":{"line":13,"column":10}},{"generated":{"line":17,"column":22},"source":"index.js","original":{"line":13,"column":21}},{"name":"$","generated":{"line":18,"column":0},"source":"index.js","original":{"line":14,"column":4}},{"generated":{"line":18,"column":6},"source":"index.js","original":{"line":14,"column":6}},{"generated":{"line":18,"column":22},"source":"index.js","original":{"line":14,"column":4}},{"name":"fadeIn","generated":{"line":18,"column":24},"source":"index.js","original":{"line":14,"column":24}},{"generated":{"line":18,"column":30},"source":"index.js","original":{"line":14,"column":4}},{"generated":{"line":18,"column":31},"source":"index.js","original":{"line":14,"column":31}},{"generated":{"line":18,"column":35},"source":"index.js","original":{"line":14,"column":4}},{"generated":{"line":18,"column":37},"source":"index.js","original":{"line":14,"column":37}},{"generated":{"line":18,"column":49},"source":"index.js","original":{"line":14,"column":48}},{"name":"$","generated":{"line":19,"column":0},"source":"index.js","original":{"line":15,"column":6}},{"generated":{"line":19,"column":8},"source":"index.js","original":{"line":15,"column":8}},{"generated":{"line":19,"column":24},"source":"index.js","original":{"line":15,"column":6}},{"name":"hide","generated":{"line":19,"column":26},"source":"index.js","original":{"line":15,"column":26}},{"generated":{"line":19,"column":30},"source":"index.js","original":{"line":15,"column":6}},{"generated":{"line":19,"column":31},"source":"index.js","original":{"line":15,"column":31}},{"generated":{"line":19,"column":34},"source":"index.js","original":{"line":15,"column":6}},{"name":"$","generated":{"line":20,"column":0},"source":"index.js","original":{"line":16,"column":6}},{"generated":{"line":20,"column":8},"source":"index.js","original":{"line":16,"column":8}},{"generated":{"line":20,"column":24},"source":"index.js","original":{"line":16,"column":6}},{"name":"animate","generated":{"line":20,"column":26},"source":"index.js","original":{"line":16,"column":26}},{"generated":{"line":20,"column":33},"source":"index.js","original":{"line":16,"column":6}},{"generated":{"line":20,"column":34},"source":"index.js","original":{"line":16,"column":34}},{"name":"width","generated":{"line":22,"column":0},"source":"index.js","original":{"line":18,"column":8}},{"generated":{"line":22,"column":15},"source":"index.js","original":{"line":18,"column":15}},{"generated":{"line":23,"column":0},"source":"index.js","original":{"line":16,"column":34}},{"generated":{"line":23,"column":7},"source":"index.js","original":{"line":16,"column":6}},{"generated":{"line":23,"column":9},"source":"index.js","original":{"line":19,"column":9}},{"generated":{"line":23,"column":12},"source":"index.js","original":{"line":16,"column":6}},{"generated":{"line":23,"column":14},"source":"index.js","original":{"line":19,"column":14}},{"generated":{"line":23,"column":26},"source":"index.js","original":{"line":19,"column":25}},{"name":"$","generated":{"line":24,"column":0},"source":"index.js","original":{"line":20,"column":8}},{"generated":{"line":24,"column":10},"source":"index.js","original":{"line":20,"column":10}},{"generated":{"line":24,"column":25},"source":"index.js","original":{"line":20,"column":8}},{"name":"animate","generated":{"line":24,"column":27},"source":"index.js","original":{"line":20,"column":27}},{"generated":{"line":24,"column":34},"source":"index.js","original":{"line":20,"column":8}},{"generated":{"line":24,"column":35},"source":"index.js","original":{"line":20,"column":35}},{"name":"height","generated":{"line":25,"column":0},"source":"index.js","original":{"line":21,"column":12}},{"generated":{"line":25,"column":18},"source":"index.js","original":{"line":21,"column":20}},{"generated":{"line":26,"column":0},"source":"index.js","original":{"line":20,"column":35}},{"generated":{"line":26,"column":9},"source":"index.js","original":{"line":20,"column":8}},{"generated":{"line":26,"column":11},"source":"index.js","original":{"line":22,"column":13}},{"generated":{"line":26,"column":14},"source":"index.js","original":{"line":20,"column":8}},{"generated":{"line":26,"column":16},"source":"index.js","original":{"line":23,"column":10}},{"generated":{"line":26,"column":28},"source":"index.js","original":{"line":23,"column":21}},{"name":"$","generated":{"line":27,"column":0},"source":"index.js","original":{"line":24,"column":12}},{"generated":{"line":27,"column":12},"source":"index.js","original":{"line":24,"column":14}},{"generated":{"line":27,"column":27},"source":"index.js","original":{"line":24,"column":12}},{"name":"animate","generated":{"line":27,"column":29},"source":"index.js","original":{"line":24,"column":31}},{"generated":{"line":27,"column":36},"source":"index.js","original":{"line":24,"column":12}},{"generated":{"line":27,"column":37},"source":"index.js","original":{"line":24,"column":39}},{"name":"width","generated":{"line":28,"column":0},"source":"index.js","original":{"line":25,"column":14}},{"generated":{"line":28,"column":19},"source":"index.js","original":{"line":25,"column":21}},{"generated":{"line":29,"column":0},"source":"index.js","original":{"line":24,"column":39}},{"generated":{"line":29,"column":11},"source":"index.js","original":{"line":24,"column":12}},{"generated":{"line":29,"column":13},"source":"index.js","original":{"line":26,"column":15}},{"generated":{"line":29,"column":16},"source":"index.js","original":{"line":24,"column":12}},{"generated":{"line":30,"column":0},"source":"index.js","original":{"line":27,"column":11}},{"generated":{"line":30,"column":9},"source":"index.js","original":{"line":20,"column":8}},{"generated":{"line":31,"column":0},"source":"index.js","original":{"line":28,"column":7}},{"generated":{"line":31,"column":7},"source":"index.js","original":{"line":16,"column":6}},{"generated":{"line":32,"column":0},"source":"index.js","original":{"line":30,"column":5}},{"generated":{"line":32,"column":5},"source":"index.js","original":{"line":14,"column":4}},{"generated":{"line":33,"column":0},"source":"index.js","original":{"line":32,"column":3}},{"generated":{"line":33,"column":3},"source":"index.js","original":{"line":9,"column":2}},{"generated":{"line":34,"column":0},"source":"index.js","original":{"line":34,"column":1}},{"generated":{"line":34,"column":1},"source":"index.js","original":{"line":5,"column":0}}],"sources":{"index.js":"import './styles/styles.scss';\nimport 'flexboxgrid';\nimport './js/text.js';\n\n$(\".features_home\").animate({\n  top: \"0%\",\n  height: \"100%\",\n}, 1000, function() {\n  $(\".features_home\").animate({\n    left: \"0px\",\n    width: \"50%\",\n\n  }, 900, function() {\n    $(\".features_text\").fadeIn(2000, function() {\n      $(\".features_text\").hide(900)\n      $(\".features_home\").animate({\n\n        width: \"35%\",\n      }, 500, function() {\n        $(\".features_img\").animate({\n            height: \"70%\",\n          }, 500,\n          function() {\n            $(\".features_img\").animate({\n              width: \"30%\",\n            }, 500)\n          })\n      })\n\n    })\n\n  })\n\n});"},"lineCount":null}},"hash":"4a7c0f8abca28ae7bfb261947e8df5d2","cacheData":{"env":{}}}